rstms_etherscan_python/__init__.py
rstms_etherscan_python/etherscan.py
rstms_etherscan_python/exceptions.py
rstms_etherscan_python/version.py
rstms_etherscan_python/configs/GOERLI-stable.json
rstms_etherscan_python/configs/KOVAN-stable.json
rstms_etherscan_python/configs/MAIN-stable.json
rstms_etherscan_python/configs/RINKEBY-stable.json
rstms_etherscan_python/configs/ROPSTEN-stable.json
rstms_etherscan_python/configs/__init__.py
rstms_etherscan_python/enums/__init__.py
rstms_etherscan_python/enums/actions_enum.py
rstms_etherscan_python/enums/fields_enum.py
rstms_etherscan_python/enums/modules_enum.py
rstms_etherscan_python/enums/tags_enum.py
rstms_etherscan_python/modules/__init__.py
rstms_etherscan_python/modules/accounts.py
rstms_etherscan_python/modules/blocks.py
rstms_etherscan_python/modules/contracts.py
rstms_etherscan_python/modules/gastracker.py
rstms_etherscan_python/modules/pro.py
rstms_etherscan_python/modules/proxy.py
rstms_etherscan_python/modules/stats.py
rstms_etherscan_python/modules/tokens.py
rstms_etherscan_python/modules/transactions.py
rstms_etherscan_python/utils/__init__.py
rstms_etherscan_python/utils/conversions.py
rstms_etherscan_python/utils/parsing.py
rstms_etherscan_python-2.1.11.dist-info/LICENSE
rstms_etherscan_python-2.1.11.dist-info/WHEEL
rstms_etherscan_python-2.1.11.dist-info/METADATA
rstms_etherscan_python-2.1.11.dist-info/RECORD
